kaizen_help/__init__.py
kaizen_help/files.py
kaizen_help/funk.py
kaizen_help/main.py
kaizen_help-0.1.1.dist-info/METADATA
kaizen_help-0.1.1.dist-info/WHEEL
kaizen_help-0.1.1.dist-info/entry_points.txt
kaizen_help-0.1.1.dist-info/RECORD
