Metadata-Version: 2.1
Name: kaizen-help
Version: 0.1.1
Summary: kaizens helper
Author: Kaizen
Author-email: shindes0321@gmail.com
Requires-Python: >=3.9,<4.0
Classifier: Programming Language :: Python :: 3
Classifier: Programming Language :: Python :: 3.9
Classifier: Programming Language :: Python :: 3.10
Classifier: Programming Language :: Python :: 3.11
Requires-Dist: typer[all] (>=0.9.0,<0.10.0)
